x_4357_make_py_mod_sideload_x/__init__.py
x_4357_make_py_mod_sideload_x/__init__.pyi
x_4357_make_py_mod_sideload_x/py.typed
x_4357_make_py_mod_sideload_x/x_cls_make_py_mod_sideload_x.py
x_4357_make_py_mod_sideload_x/x_cls_make_py_mod_sideload_x.pyi
x_4357_make_py_mod_sideload_x-0.20.17.dist-info/METADATA
x_4357_make_py_mod_sideload_x-0.20.17.dist-info/WHEEL
x_4357_make_py_mod_sideload_x-0.20.17.dist-info/top_level.txt
x_4357_make_py_mod_sideload_x-0.20.17.dist-info/RECORD
